flask_pie/__init__.py
flask_pie/ext.py
flask_pie/temp.py
flask_pie/testing.py
flask_pie/utils.py
flask_pie/datasets/__init__.py
flask_pie/datasets/lasla.py
flask_pie/disambiguator/__init__.py
flask_pie/disambiguator/autocat.py
flask_pie/disambiguator/proto.py
flask_pie/disambiguator/tarte.py
flask_pie/formatters/__init__.py
flask_pie/formatters/glue.py
flask_pie-0.1.2.dist-info/METADATA
flask_pie-0.1.2.dist-info/WHEEL
flask_pie-0.1.2.dist-info/entry_points.txt
flask_pie-0.1.2.dist-info/top_level.txt
flask_pie-0.1.2.dist-info/RECORD
